aioapcaccess/__init__.py
aioapcaccess/py.typed
aioapcaccess-0.5.0.dist-info/LICENSE
aioapcaccess-0.5.0.dist-info/METADATA
aioapcaccess-0.5.0.dist-info/WHEEL
aioapcaccess-0.5.0.dist-info/top_level.txt
aioapcaccess-0.5.0.dist-info/RECORD
