Metadata-Version: 2.1
Name: aioapcaccess
Version: 0.5.0
Summary: Async version of apcaccess library implemented in python.
Author-email: Yuxin Wang <yuxinwang.dev@gmail.com>
License: MIT
Classifier: Programming Language :: Python :: 3
Classifier: License :: OSI Approved :: MIT License
Classifier: Operating System :: OS Independent
Requires-Python: >=3.8
License-File: LICENSE
Provides-Extra: dev
Requires-Dist: pytest >=6.0 ; extra == 'dev'
Requires-Dist: pytest-cov ; extra == 'dev'
Requires-Dist: pytest-asyncio >=0.17 ; extra == 'dev'
